RaspyTweak/__init__.py
RaspyTweak/__todo__.py
RaspyTweak/constants.py
RaspyTweak/cpu.py
RaspyTweak/disk.py
RaspyTweak/errors.py
RaspyTweak/gpio.py
RaspyTweak/memory.py
RaspyTweak/network.py
RaspyTweak/system.py
RaspyTweak-0.0.1a1.dist-info/METADATA
RaspyTweak-0.0.1a1.dist-info/WHEEL
RaspyTweak-0.0.1a1.dist-info/top_level.txt
RaspyTweak-0.0.1a1.dist-info/RECORD
